{
  "protocol_version" : "0.0.6",
  "configuration" : {
    "version" : "(6.13.0) (explicit/b6ecd9a4)",
    "tlc" : "__thread",
    "sigsgev" : "normal",
    "notifications" : "kqueue",
    "architecture" : "arm64",
    "disabled_features" : "com,shared_perfcounters",
    "smallconfig" : "disabled",
    "bigarrays" : "disabled",
    "softdebug" : "enabled",
    "interpreter" : "enabled",
    "llvm_support" : "disabled",
    "suspend" : "preemptive"
  },
  "memory" : {
    "Resident Size" : "584646656",
    "Virtual Size" : "423801208832",
    "minor_gc_time" : "0",
    "major_gc_time" : "668962",
    "minor_gc_count" : "0",
    "major_gc_count" : "65",
    "major_gc_time_concurrent" : "0"
 },
  "threads" : [
 {
    "is_managed" : false,
    "offset_free_hash" : "0x0",
    "offset_rich_hash" : "0x0",
    "crashed" : false,
    "native_thread_id" : "0x17fac7000",
    "thread_info_addr" : "0x1598ce000",
    "thread_name" : "Finalizer",
    "ctx" : {
      "IP" : "0x189562170",
      "SP" : "0x17fac6dd0",
      "BP" : "0x17fac6e50"
  },
    "unmanaged_frames" : [
  {
      "is_managed" : "false",
      "native_address" : "0x1433051a0",
      "native_offset" : "0x00000"
   }
,
  {
      "is_managed" : "false",
      "native_address" : "0x14343c518",
      "native_offset" : "0x00000"
   }
,
  {
      "is_managed" : "false",
      "native_address" : "0x14343c874",
      "native_offset" : "0x00000"
   }
,
  {
      "is_managed" : "false",
      "native_address" : "0x14343c63c",
      "native_offset" : "0x00000"
   }
,
  {
      "is_managed" : "false",
      "native_address" : "0x1433463d0",
      "native_offset" : "0x00000"
   }
,
  {
      "is_managed" : "false",
      "native_address" : "0x1895d3584",
      "native_offset" : "0x00000"
   }
,
  {
      "is_managed" : "false",
      "native_address" : "0x14347616c",
      "native_offset" : "0x00000"
   }
,
  {
      "is_managed" : "false",
      "native_address" : "0x14343d284",
      "native_offset" : "0x00000"
   }
,
  {
      "is_managed" : "false",
      "native_address" : "0x14343d130",
      "native_offset" : "0x00000"
   }
,
  {
      "is_managed" : "false",
      "native_address" : "0x1434bccf8",
      "native_offset" : "0x00000"
   }
,
  {
      "is_managed" : "false",
      "native_address" : "0x1434bcc80",
      "native_offset" : "0x00000"
   }
,
  {
      "is_managed" : "false",
      "native_address" : "0x1895a2f94",
      "native_offset" : "0x00000"
   }
,
  {
      "is_managed" : "false",
      "native_address" : "0x18959dd34",
      "native_offset" : "0x00000"
   }

  ]
 },
 {
    "is_managed" : false,
    "offset_free_hash" : "0x0",
    "offset_rich_hash" : "0x0",
    "crashed" : false,
    "native_thread_id" : "0x16de27000",
    "thread_info_addr" : "0x150c83800",
    "thread_name" : "tid_20b43",
    "ctx" : {
      "IP" : "0x189562170",
      "SP" : "0x16de26d90",
      "BP" : "0x16de26da0"
  },
    "unmanaged_frames" : [
  {
      "is_managed" : "false",
      "native_address" : "0x1433051a0",
      "native_offset" : "0x00000"
   }
,
  {
      "is_managed" : "false",
      "native_address" : "0x14343c518",
      "native_offset" : "0x00000"
   }
,
  {
      "is_managed" : "false",
      "native_address" : "0x14343c874",
      "native_offset" : "0x00000"
   }
,
  {
      "is_managed" : "false",
      "native_address" : "0x14343c63c",
      "native_offset" : "0x00000"
   }
,
  {
      "is_managed" : "false",
      "native_address" : "0x1433463d0",
      "native_offset" : "0x00000"
   }
,
  {
      "is_managed" : "false",
      "native_address" : "0x1895d3584",
      "native_offset" : "0x00000"
   }
,
  {
      "is_managed" : "false",
      "native_address" : "0x1893f2984",
      "native_offset" : "0x00000"
   }
,
  {
      "is_managed" : "false",
      "native_address" : "0x1893f3034",
      "native_offset" : "0x00000"
   }
,
  {
      "is_managed" : "false",
      "native_address" : "0x105396240",
      "native_offset" : "0x00000"
   }
,
  {
      "is_managed" : "false",
      "native_address" : "0x102d23844",
      "native_offset" : "0x00000"
   }
,
  {
      "is_managed" : "false",
      "native_address" : "0x10312904c",
      "native_offset" : "0x00000"
   }
,
  {
      "is_managed" : "false",
      "native_address" : "0x103128fe8",
      "native_offset" : "0x00000"
   }
,
  {
      "is_managed" : "false",
      "native_address" : "0x1032da6f4",
      "native_offset" : "0x00000"
   }
,
  {
      "is_managed" : "false",
      "native_address" : "0x1895a2f94",
      "native_offset" : "0x00000"
   }
,
  {
      "is_managed" : "false",
      "native_address" : "0x18959dd34",
      "native_offset" : "0x00000"
   }

  ]
 },
 {
    "is_managed" : true,
    "offset_free_hash" : "0x169a4c1832",
    "offset_rich_hash" : "0x169a4c1fb5",
    "crashed" : true,
    "native_thread_id" : "0x1f12afac0",
    "thread_info_addr" : "0x159845e00",
    "thread_name" : "tid_103",
    "ctx" : {
      "IP" : "0x10322d07c",
      "SP" : "0x16d649d00",
      "BP" : "0x16d649ec0"
  },
    "managed_frames" : [
  {
      "is_managed" : "false",
      "native_address" : "unregistered"
   }
,
  {
      "is_managed" : "true",
      "guid" : "3C9AC2DF-4D3B-4342-B1D6-8F6A776F43A3",
      "token" : "0x00000",
      "native_offset" : "0x0",
      "filename" : "UnityEngine.CoreModule.dll",
      "sizeofimage" : "0x17c000",
      "timestamp" : "0xfb397a6e",
      "il_offset" : "0xffffffff"
   }
,
  {
      "is_managed" : "true",
      "guid" : "3C9AC2DF-4D3B-4342-B1D6-8F6A776F43A3",
      "token" : "0x6002b15",
      "native_offset" : "0x0",
      "filename" : "UnityEngine.CoreModule.dll",
      "sizeofimage" : "0x17c000",
      "timestamp" : "0xfb397a6e",
      "il_offset" : "0x00000"
   }
,
  {
      "is_managed" : "true",
      "guid" : "3C9AC2DF-4D3B-4342-B1D6-8F6A776F43A3",
      "token" : "0x6002b3b",
      "native_offset" : "0x0",
      "filename" : "UnityEngine.CoreModule.dll",
      "sizeofimage" : "0x17c000",
      "timestamp" : "0xfb397a6e",
      "il_offset" : "0x00008"
   }
,
  {
      "is_managed" : "true",
      "guid" : "8FB14C82-33FA-4768-AFF0-072D7E0D683B",
      "token" : "0x60007f1",
      "native_offset" : "0x0",
      "filename" : "Unity.RenderPipelines.Universal.Runtime.dll",
      "sizeofimage" : "0xd0000",
      "timestamp" : "0xc25a9dfc",
      "il_offset" : "0x001f4"
   }
,
  {
      "is_managed" : "true",
      "guid" : "8FB14C82-33FA-4768-AFF0-072D7E0D683B",
      "token" : "0x60007ef",
      "native_offset" : "0x0",
      "filename" : "Unity.RenderPipelines.Universal.Runtime.dll",
      "sizeofimage" : "0xd0000",
      "timestamp" : "0xc25a9dfc",
      "il_offset" : "0x00034"
   }
,
  {
      "is_managed" : "true",
      "guid" : "8FB14C82-33FA-4768-AFF0-072D7E0D683B",
      "token" : "0x60007ee",
      "native_offset" : "0x0",
      "filename" : "Unity.RenderPipelines.Universal.Runtime.dll",
      "sizeofimage" : "0xd0000",
      "timestamp" : "0xc25a9dfc",
      "il_offset" : "0x00018"
   }
,
  {
      "is_managed" : "true",
      "guid" : "8FB14C82-33FA-4768-AFF0-072D7E0D683B",
      "token" : "0x60007ea",
      "native_offset" : "0x0",
      "filename" : "Unity.RenderPipelines.Universal.Runtime.dll",
      "sizeofimage" : "0xd0000",
      "timestamp" : "0xc25a9dfc",
      "il_offset" : "0x0011d"
   }
,
  {
      "is_managed" : "true",
      "guid" : "3C9AC2DF-4D3B-4342-B1D6-8F6A776F43A3",
      "token" : "0x6002a8b",
      "native_offset" : "0x0",
      "filename" : "UnityEngine.CoreModule.dll",
      "sizeofimage" : "0x17c000",
      "timestamp" : "0xfb397a6e",
      "il_offset" : "0x0001c"
   }
,
  {
      "is_managed" : "true",
      "guid" : "3C9AC2DF-4D3B-4342-B1D6-8F6A776F43A3",
      "token" : "0x6002ad2",
      "native_offset" : "0x0",
      "filename" : "UnityEngine.CoreModule.dll",
      "sizeofimage" : "0x17c000",
      "timestamp" : "0xfb397a6e",
      "il_offset" : "0x00047"
   }
,
  {
      "is_managed" : "true",
      "guid" : "3C9AC2DF-4D3B-4342-B1D6-8F6A776F43A3",
      "token" : "0x00000",
      "native_offset" : "0x0",
      "filename" : "UnityEngine.CoreModule.dll",
      "sizeofimage" : "0x17c000",
      "timestamp" : "0xfb397a6e",
      "il_offset" : "0x0002a"
   }
,
  {
      "is_managed" : "false",
      "native_address" : "unregistered"
   }
,
  {
      "is_managed" : "true",
      "guid" : "3C9AC2DF-4D3B-4342-B1D6-8F6A776F43A3",
      "token" : "0x00000",
      "native_offset" : "0x0",
      "filename" : "UnityEngine.CoreModule.dll",
      "sizeofimage" : "0x17c000",
      "timestamp" : "0xfb397a6e",
      "il_offset" : "0xffffffff"
   }
,
  {
      "is_managed" : "true",
      "guid" : "C8EEDA6B-ABDD-44A1-BEEF-7AE3B1AC7095",
      "token" : "0x6004d44",
      "native_offset" : "0x0",
      "filename" : "UnityEditor.CoreModule.dll",
      "sizeofimage" : "0x95a000",
      "timestamp" : "0xa7124c2f",
      "il_offset" : "0x000fb"
   }
,
  {
      "is_managed" : "true",
      "guid" : "C8EEDA6B-ABDD-44A1-BEEF-7AE3B1AC7095",
      "token" : "0x60046ea",
      "native_offset" : "0x0",
      "filename" : "UnityEditor.CoreModule.dll",
      "sizeofimage" : "0x95a000",
      "timestamp" : "0xa7124c2f",
      "il_offset" : "0x00189"
   }
,
  {
      "is_managed" : "true",
      "guid" : "C8EEDA6B-ABDD-44A1-BEEF-7AE3B1AC7095",
      "token" : "0x60046eb",
      "native_offset" : "0x0",
      "filename" : "UnityEditor.CoreModule.dll",
      "sizeofimage" : "0x95a000",
      "timestamp" : "0xa7124c2f",
      "il_offset" : "0x00045"
   }
,
  {
      "is_managed" : "true",
      "guid" : "C8EEDA6B-ABDD-44A1-BEEF-7AE3B1AC7095",
      "token" : "0x6001e20",
      "native_offset" : "0x0",
      "filename" : "UnityEditor.CoreModule.dll",
      "sizeofimage" : "0x95a000",
      "timestamp" : "0xa7124c2f",
      "il_offset" : "0x0009f"
   }
,
  {
      "is_managed" : "true",
      "guid" : "C8EEDA6B-ABDD-44A1-BEEF-7AE3B1AC7095",
      "token" : "0x6001e1f",
      "native_offset" : "0x0",
      "filename" : "UnityEditor.CoreModule.dll",
      "sizeofimage" : "0x95a000",
      "timestamp" : "0xa7124c2f",
      "il_offset" : "0x00001"
   }
,
  {
      "is_managed" : "true",
      "guid" : "C8EEDA6B-ABDD-44A1-BEEF-7AE3B1AC7095",
      "token" : "0x00000",
      "native_offset" : "0x0",
      "filename" : "UnityEditor.CoreModule.dll",
      "sizeofimage" : "0x95a000",
      "timestamp" : "0xa7124c2f",
      "il_offset" : "0x0002a"
   }

  ],
  "unmanaged_frames" : [
 {
    "is_managed" : "false",
    "native_address" : "0x1433051a0",
    "native_offset" : "0x00000"
  }
,
 {
    "is_managed" : "false",
    "native_address" : "0x14343c518",
    "native_offset" : "0x00000"
  }
,
 {
    "is_managed" : "false",
    "native_address" : "0x14343c874",
    "native_offset" : "0x00000"
  }
,
 {
    "is_managed" : "false",
    "native_address" : "0x14343ce64",
    "native_offset" : "0x00000"
  }
,
 {
    "is_managed" : "false",
    "native_address" : "0x14334721c",
    "native_offset" : "0x00000"
  }
,
 {
    "is_managed" : "false",
    "native_address" : "0x143309338",
    "native_offset" : "0x00000"
  }
,
 {
    "is_managed" : "false",
    "native_address" : "0x143291ac8",
    "native_offset" : "0x00000"
  }
,
 {
    "is_managed" : "false",
    "native_address" : "0x1895d3584",
    "native_offset" : "0x00000"
  }
,
 {
    "is_managed" : "false",
    "native_address" : "0x1032471d8",
    "native_offset" : "0x00000"
  }
,
 {
    "is_managed" : "false",
    "native_address" : "0x10323604c",
    "native_offset" : "0x00000"
  }
,
 {
    "is_managed" : "false",
    "native_address" : "0x1031a8968",
    "native_offset" : "0x00000"
  }
,
 {
    "is_managed" : "false",
    "native_address" : "0x10303c9d4",
    "native_offset" : "0x00000"
  }
,
 {
    "is_managed" : "false",
    "native_address" : "0x103040f44",
    "native_offset" : "0x00000"
  }
,
 {
    "is_managed" : "false",
    "native_address" : "0x103042acc",
    "native_offset" : "0x00000"
  }
,
 {
    "is_managed" : "false",
    "native_address" : "0x103047588",
    "native_offset" : "0x00000"
  }
,
 {
    "is_managed" : "false",
    "native_address" : "0x1033aa6f4",
    "native_offset" : "0x00000"
  }
,
 {
    "is_managed" : "false",
    "native_address" : "0x1030451b0",
    "native_offset" : "0x00000"
  }
,
 {
    "is_managed" : "false",
    "native_address" : "0x103044d08",
    "native_offset" : "0x00000"
  }
,
 {
    "is_managed" : "false",
    "native_address" : "0x1030351cc",
    "native_offset" : "0x00000"
  }
,
 {
    "is_managed" : "true",
    "guid" : "3C9AC2DF-4D3B-4342-B1D6-8F6A776F43A3",
    "token" : "0x00000",
    "native_offset" : "0x0",
    "filename" : "UnityEngine.CoreModule.dll",
    "sizeofimage" : "0x17c000",
    "timestamp" : "0xfb397a6e",
    "il_offset" : "0x00000"
  }
,
 {
    "is_managed" : "true",
    "guid" : "3C9AC2DF-4D3B-4342-B1D6-8F6A776F43A3",
    "token" : "0x6002b15",
    "native_offset" : "0x0",
    "filename" : "UnityEngine.CoreModule.dll",
    "sizeofimage" : "0x17c000",
    "timestamp" : "0xfb397a6e",
    "il_offset" : "0x00000"
  }
,
 {
    "is_managed" : "true",
    "guid" : "3C9AC2DF-4D3B-4342-B1D6-8F6A776F43A3",
    "token" : "0x6002b3b",
    "native_offset" : "0x0",
    "filename" : "UnityEngine.CoreModule.dll",
    "sizeofimage" : "0x17c000",
    "timestamp" : "0xfb397a6e",
    "il_offset" : "0x00000"
  }
,
 {
    "is_managed" : "true",
    "guid" : "8FB14C82-33FA-4768-AFF0-072D7E0D683B",
    "token" : "0x60007f1",
    "native_offset" : "0x0",
    "filename" : "Unity.RenderPipelines.Universal.Runtime.dll",
    "sizeofimage" : "0xd0000",
    "timestamp" : "0xc25a9dfc",
    "il_offset" : "0x00000"
  }
,
 {
    "is_managed" : "true",
    "guid" : "8FB14C82-33FA-4768-AFF0-072D7E0D683B",
    "token" : "0x60007ef",
    "native_offset" : "0x0",
    "filename" : "Unity.RenderPipelines.Universal.Runtime.dll",
    "sizeofimage" : "0xd0000",
    "timestamp" : "0xc25a9dfc",
    "il_offset" : "0x00000"
  }
,
 {
    "is_managed" : "true",
    "guid" : "8FB14C82-33FA-4768-AFF0-072D7E0D683B",
    "token" : "0x60007ee",
    "native_offset" : "0x0",
    "filename" : "Unity.RenderPipelines.Universal.Runtime.dll",
    "sizeofimage" : "0xd0000",
    "timestamp" : "0xc25a9dfc",
    "il_offset" : "0x00000"
  }
,
 {
    "is_managed" : "true",
    "guid" : "8FB14C82-33FA-4768-AFF0-072D7E0D683B",
    "token" : "0x60007ea",
    "native_offset" : "0x0",
    "filename" : "Unity.RenderPipelines.Universal.Runtime.dll",
    "sizeofimage" : "0xd0000",
    "timestamp" : "0xc25a9dfc",
    "il_offset" : "0x00000"
  }
,
 {
    "is_managed" : "true",
    "guid" : "3C9AC2DF-4D3B-4342-B1D6-8F6A776F43A3",
    "token" : "0x6002a8b",
    "native_offset" : "0x0",
    "filename" : "UnityEngine.CoreModule.dll",
    "sizeofimage" : "0x17c000",
    "timestamp" : "0xfb397a6e",
    "il_offset" : "0x00000"
  }
,
 {
    "is_managed" : "true",
    "guid" : "3C9AC2DF-4D3B-4342-B1D6-8F6A776F43A3",
    "token" : "0x6002ad2",
    "native_offset" : "0x0",
    "filename" : "UnityEngine.CoreModule.dll",
    "sizeofimage" : "0x17c000",
    "timestamp" : "0xfb397a6e",
    "il_offset" : "0x00000"
  }
,
 {
    "is_managed" : "true",
    "guid" : "3C9AC2DF-4D3B-4342-B1D6-8F6A776F43A3",
    "token" : "0x00000",
    "native_offset" : "0x0",
    "filename" : "UnityEngine.CoreModule.dll",
    "sizeofimage" : "0x17c000",
    "timestamp" : "0xfb397a6e",
    "il_offset" : "0x00000"
  }
,
 {
    "is_managed" : "false",
    "native_address" : "0x143294d88",
    "native_offset" : "0x00000"
  }
,
 {
    "is_managed" : "false",
    "native_address" : "0x14341b24c",
    "native_offset" : "0x00000"
  }
,
 {
    "is_managed" : "false",
    "native_address" : "0x14341b16c",
    "native_offset" : "0x00000"
  }
,
 {
    "is_managed" : "false",
    "native_address" : "0x1034acb04",
    "native_offset" : "0x00000"
  }
,
 {
    "is_managed" : "false",
    "native_address" : "0x103487c04",
    "native_offset" : "0x00000"
  }
,
 {
    "is_managed" : "false",
    "native_address" : "0x103036290",
    "native_offset" : "0x00000"
  }
,
 {
    "is_managed" : "false",
    "native_address" : "0x102e10cb8",
    "native_offset" : "0x00000"
  }
,
 {
    "is_managed" : "false",
    "native_address" : "0x102e10420",
    "native_offset" : "0x00000"
  }
,
 {
    "is_managed" : "false",
    "native_address" : "0x102e21a68",
    "native_offset" : "0x00000"
  }
,
 {
    "is_managed" : "false",
    "native_address" : "0x10279f314",
    "native_offset" : "0x00000"
  }
,
 {
    "is_managed" : "true",
    "guid" : "3C9AC2DF-4D3B-4342-B1D6-8F6A776F43A3",
    "token" : "0x00000",
    "native_offset" : "0x0",
    "filename" : "UnityEngine.CoreModule.dll",
    "sizeofimage" : "0x17c000",
    "timestamp" : "0xfb397a6e",
    "il_offset" : "0x00000"
  }
,
 {
    "is_managed" : "true",
    "guid" : "C8EEDA6B-ABDD-44A1-BEEF-7AE3B1AC7095",
    "token" : "0x6004d44",
    "native_offset" : "0x0",
    "filename" : "UnityEditor.CoreModule.dll",
    "sizeofimage" : "0x95a000",
    "timestamp" : "0xa7124c2f",
    "il_offset" : "0x00000"
  }
,
 {
    "is_managed" : "true",
    "guid" : "C8EEDA6B-ABDD-44A1-BEEF-7AE3B1AC7095",
    "token" : "0x60046ea",
    "native_offset" : "0x0",
    "filename" : "UnityEditor.CoreModule.dll",
    "sizeofimage" : "0x95a000",
    "timestamp" : "0xa7124c2f",
    "il_offset" : "0x00000"
  }
,
 {
    "is_managed" : "true",
    "guid" : "C8EEDA6B-ABDD-44A1-BEEF-7AE3B1AC7095",
    "token" : "0x60046eb",
    "native_offset" : "0x0",
    "filename" : "UnityEditor.CoreModule.dll",
    "sizeofimage" : "0x95a000",
    "timestamp" : "0xa7124c2f",
    "il_offset" : "0x00000"
  }
,
 {
    "is_managed" : "true",
    "guid" : "C8EEDA6B-ABDD-44A1-BEEF-7AE3B1AC7095",
    "token" : "0x6001e20",
    "native_offset" : "0x0",
    "filename" : "UnityEditor.CoreModule.dll",
    "sizeofimage" : "0x95a000",
    "timestamp" : "0xa7124c2f",
    "il_offset" : "0x00000"
  }
,
 {
    "is_managed" : "true",
    "guid" : "C8EEDA6B-ABDD-44A1-BEEF-7AE3B1AC7095",
    "token" : "0x6001e1f",
    "native_offset" : "0x0",
    "filename" : "UnityEditor.CoreModule.dll",
    "sizeofimage" : "0x95a000",
    "timestamp" : "0xa7124c2f",
    "il_offset" : "0x00000"
  }
,
 {
    "is_managed" : "true",
    "guid" : "C8EEDA6B-ABDD-44A1-BEEF-7AE3B1AC7095",
    "token" : "0x00000",
    "native_offset" : "0x0",
    "filename" : "UnityEditor.CoreModule.dll",
    "sizeofimage" : "0x95a000",
    "timestamp" : "0xa7124c2f",
    "il_offset" : "0x00000"
  }
,
 {
    "is_managed" : "false",
    "native_address" : "0x143294d88",
    "native_offset" : "0x00000"
  }
,
 {
    "is_managed" : "false",
    "native_address" : "0x14341b24c",
    "native_offset" : "0x00000"
  }
,
 {
    "is_managed" : "false",
    "native_address" : "0x14341b16c",
    "native_offset" : "0x00000"
  }
,
 {
    "is_managed" : "false",
    "native_address" : "0x1034acb04",
    "native_offset" : "0x00000"
  }
,
 {
    "is_managed" : "false",
    "native_address" : "0x103487c04",
    "native_offset" : "0x00000"
  }
,
 {
    "is_managed" : "false",
    "native_address" : "0x1047827e4",
    "native_offset" : "0x00000"
  }
,
 {
    "is_managed" : "false",
    "native_address" : "0x10477812c",
    "native_offset" : "0x00000"
  }
,
 {
    "is_managed" : "false",
    "native_address" : "0x1047c232c",
    "native_offset" : "0x00000"
  }
,
 {
    "is_managed" : "false",
    "native_address" : "0x1047c14a8",
    "native_offset" : "0x00000"
  }
,
 {
    "is_managed" : "false",
    "native_address" : "0x10530b8a4",
    "native_offset" : "0x00000"
  }
,
 {
    "is_managed" : "false",
    "native_address" : "0x1047ed458",
    "native_offset" : "0x00000"
  }
,
 {
    "is_managed" : "false",
    "native_address" : "0x104894310",
    "native_offset" : "0x00000"
  }
,
 {
    "is_managed" : "false",
    "native_address" : "0x1893f23e8",
    "native_offset" : "0x00000"
  }
,
 {
    "is_managed" : "false",
    "native_address" : "0x1894019b0",
    "native_offset" : "0x00000"
  }
,
 {
    "is_managed" : "false",
    "native_address" : "0x1893f23e8",
    "native_offset" : "0x00000"
  }
,
 {
    "is_managed" : "false",
    "native_address" : "0x189400bb8",
    "native_offset" : "0x00000"
  }
,
 {
    "is_managed" : "false",
    "native_address" : "0x1894007cc",
    "native_offset" : "0x00000"
  }
,
 {
    "is_managed" : "false",
    "native_address" : "0x1896c34ac",
    "native_offset" : "0x00000"
  }
,
 {
    "is_managed" : "false",
    "native_address" : "0x189680c30",
    "native_offset" : "0x00000"
  }
,
 {
    "is_managed" : "false",
    "native_address" : "0x18967fe0c",
    "native_offset" : "0x00000"
  }
,
 {
    "is_managed" : "false",
    "native_address" : "0x193e1b000",
    "native_offset" : "0x00000"
  }
,
 {
    "is_managed" : "false",
    "native_address" : "0x193e1ae3c",
    "native_offset" : "0x00000"
  }
,
 {
    "is_managed" : "false",
    "native_address" : "0x193e1ab94",
    "native_offset" : "0x00000"
  }
,
 {
    "is_managed" : "false",
    "native_address" : "0x18ced8970",
    "native_offset" : "0x00000"
  }
,
 {
    "is_managed" : "false",
    "native_address" : "0x18d6cadec",
    "native_offset" : "0x00000"
  }
,
 {
    "is_managed" : "false",
    "native_address" : "0x18cecbcb8",
    "native_offset" : "0x00000"
  }
,
 {
    "is_managed" : "false",
    "native_address" : "0x18cea2f54",
    "native_offset" : "0x00000"
  }
,
 {
    "is_managed" : "false",
    "native_address" : "0x1052ed8d0",
    "native_offset" : "0x00000"
  }
,
 {
    "is_managed" : "false",
    "native_address" : "0x1052edc1c",
    "native_offset" : "0x00000"
  }
,
 {
    "is_managed" : "false",
    "native_address" : "0x18921a0e0",
    "native_offset" : "0x00000"
  }

 ]
},
{
  "is_managed" : false,
  "offset_free_hash" : "0x0",
  "offset_rich_hash" : "0x0",
  "crashed" : false,
  "native_thread_id" : "0x17fcd3000",
  "thread_info_addr" : "0x1590ea800",
  "thread_name" : "Debugger agent",
  "ctx" : {
    "IP" : "0x18956ab44",
    "SP" : "0x17fcd2aa0",
    "BP" : "0x17fcd2ae0"
 },
  "unmanaged_frames" : [
 {
    "is_managed" : "false",
    "native_address" : "0x1433051a0",
    "native_offset" : "0x00000"
  }
,
 {
    "is_managed" : "false",
    "native_address" : "0x14343c518",
    "native_offset" : "0x00000"
  }
,
 {
    "is_managed" : "false",
    "native_address" : "0x14343c874",
    "native_offset" : "0x00000"
  }
,
 {
    "is_managed" : "false",
    "native_address" : "0x14343c63c",
    "native_offset" : "0x00000"
  }
,
 {
    "is_managed" : "false",
    "native_address" : "0x1433463d0",
    "native_offset" : "0x00000"
  }
,
 {
    "is_managed" : "false",
    "native_address" : "0x1895d3584",
    "native_offset" : "0x00000"
  }
,
 {
    "is_managed" : "false",
    "native_address" : "0x14337559c",
    "native_offset" : "0x00000"
  }
,
 {
    "is_managed" : "false",
    "native_address" : "0x14336c198",
    "native_offset" : "0x00000"
  }
,
 {
    "is_managed" : "false",
    "native_address" : "0x14343d284",
    "native_offset" : "0x00000"
  }
,
 {
    "is_managed" : "false",
    "native_address" : "0x14343d130",
    "native_offset" : "0x00000"
  }
,
 {
    "is_managed" : "false",
    "native_address" : "0x1434bccf8",
    "native_offset" : "0x00000"
  }
,
 {
    "is_managed" : "false",
    "native_address" : "0x1434bcc80",
    "native_offset" : "0x00000"
  }
,
 {
    "is_managed" : "false",
    "native_address" : "0x1895a2f94",
    "native_offset" : "0x00000"
  }
,
 {
    "is_managed" : "false",
    "native_address" : "0x18959dd34",
    "native_offset" : "0x00000"
  }

 ]
},
{
  "is_managed" : false,
  "offset_free_hash" : "0x0",
  "offset_rich_hash" : "0x0",
  "crashed" : false,
  "native_thread_id" : "0x17dfd3000",
  "thread_info_addr" : "0x15944b600",
  "thread_name" : "tid_ad03",
  "ctx" : {
    "IP" : "0x189562170",
    "SP" : "0x17dfd2d10",
    "BP" : "0x17dfd2d20"
 },
  "unmanaged_frames" : [
 {
    "is_managed" : "false",
    "native_address" : "0x1433051a0",
    "native_offset" : "0x00000"
  }
,
 {
    "is_managed" : "false",
    "native_address" : "0x14343c518",
    "native_offset" : "0x00000"
  }
,
 {
    "is_managed" : "false",
    "native_address" : "0x14343c874",
    "native_offset" : "0x00000"
  }
,
 {
    "is_managed" : "false",
    "native_address" : "0x14343c63c",
    "native_offset" : "0x00000"
  }
,
 {
    "is_managed" : "false",
    "native_address" : "0x1433463d0",
    "native_offset" : "0x00000"
  }
,
 {
    "is_managed" : "false",
    "native_address" : "0x1895d3584",
    "native_offset" : "0x00000"
  }
,
 {
    "is_managed" : "false",
    "native_address" : "0x1893f2984",
    "native_offset" : "0x00000"
  }
,
 {
    "is_managed" : "false",
    "native_address" : "0x1893f3034",
    "native_offset" : "0x00000"
  }
,
 {
    "is_managed" : "false",
    "native_address" : "0x105396240",
    "native_offset" : "0x00000"
  }
,
 {
    "is_managed" : "false",
    "native_address" : "0x103073854",
    "native_offset" : "0x00000"
  }
,
 {
    "is_managed" : "false",
    "native_address" : "0x103074b34",
    "native_offset" : "0x00000"
  }
,
 {
    "is_managed" : "false",
    "native_address" : "0x1032da6f4",
    "native_offset" : "0x00000"
  }
,
 {
    "is_managed" : "false",
    "native_address" : "0x1895a2f94",
    "native_offset" : "0x00000"
  }
,
 {
    "is_managed" : "false",
    "native_address" : "0x18959dd34",
    "native_offset" : "0x00000"
  }

 ]
}
]
}